audio_carver/__init__.py
audio_carver/audio_conversion.py
audio_carver/main.py
audio_carver/seam_carving.py
audio_carver/spectrogram_analysis.py
AudioCarver-0.1.0.dist-info/LICENSE
AudioCarver-0.1.0.dist-info/METADATA
AudioCarver-0.1.0.dist-info/WHEEL
AudioCarver-0.1.0.dist-info/entry_points.txt
AudioCarver-0.1.0.dist-info/top_level.txt
AudioCarver-0.1.0.dist-info/RECORD
