Metadata-Version: 2.1
Name: AudioCarver
Version: 0.1.0
Summary: A library built to carve out minimum seams from an audio file
Home-page: https://github.com/Aloosha2/AudioCarver
Author: Alicja Misiuda
Author-email: alicjam@uw.edu
Project-URL: Record of Changes, https://github.com/Aloosha2/AudioCarver/CHANGELOG.md
Project-URL: Source Code, https://github.com/Aloosha2/AudioCarver/AudioCarver
Classifier: Development Status :: 3 - Alpha
Classifier: Intended Audience :: Developers
Classifier: Intended Audience :: Science/Research
Classifier: License :: OSI Approved :: MIT License
Classifier: Programming Language :: Python :: 3
Classifier: Programming Language :: Python :: 3.6
Classifier: Programming Language :: Python :: 3.7
Classifier: Programming Language :: Python :: 3.8
Classifier: Programming Language :: Python :: 3.9
Classifier: Programming Language :: Python :: 3.10
Classifier: Operating System :: OS Independent
Classifier: Topic :: Multimedia :: Sound/Audio :: Analysis
Classifier: Topic :: Software Development :: Libraries :: Python Modules
Requires-Python: >=3.6
License-File: LICENSE
Requires-Dist: numpy
Requires-Dist: librosa
Requires-Dist: soundfile
Requires-Dist: numba
Requires-Dist: argparse
